{"GeneratedCodeFiles":[],"GeneratedXamlFiles":["C:\\Users\\ricar\\OneDrive\\Documentos\\GitHub\\TaskManager\\TaskManager.UI.Maui\\obj\\Debug\\net8.0-windows10.0.19041.0\\win10-x64\\Platforms\\Windows\\App.xaml"],"GeneratedXbfFiles":["C:\\Users\\ricar\\OneDrive\\Documentos\\GitHub\\TaskManager\\TaskManager.UI.Maui\\obj\\Debug\\net8.0-windows10.0.19041.0\\win10-x64\\Platforms\\Windows\\App.xbf"],"GeneratedXamlPagesFiles":[],"MSBuildLogEntries":[{"SubCategory":null,"ErrorCode":null,"HelpKeyword":null,"File":null,"LineNumber":0,"ColumnNumber":0,"EndLineNumber":0,"EndColumnNumber":0,"Message":"Xaml Compiler Marker: 14:58:59: 315 perfXC_StartPass2, TaskManager.UI.Maui"},{"SubCategory":null,"ErrorCode":null,"HelpKeyword":null,"File":null,"LineNumber":0,"ColumnNumber":0,"EndLineNumber":0,"EndColumnNumber":0,"Message":"Xaml Compiler Marker: 14:58:59: 334 perfXC_FingerprintCheck, Using managed HashForWinMD"},{"SubCategory":null,"ErrorCode":null,"HelpKeyword":null,"File":null,"LineNumber":0,"ColumnNumber":0,"EndLineNumber":0,"EndColumnNumber":0,"Message":"Xaml Compiler Marker: 14:58:59: 423 perfXC_FingerprintCheck, Using managed HashForWinMD"},{"SubCategory":null,"ErrorCode":null,"HelpKeyword":null,"File":null,"LineNumber":0,"ColumnNumber":0,"EndLineNumber":0,"EndColumnNumber":0,"Message":"Xaml Compiler Marker: 14:58:59: 425 perfXC_FingerprintCheck, Using managed HashForWinMD"},{"SubCategory":null,"ErrorCode":null,"HelpKeyword":null,"File":null,"LineNumber":0,"ColumnNumber":0,"EndLineNumber":0,"EndColumnNumber":0,"Message":"Xaml Compiler Marker: 14:58:59: 427 perfXC_RestoredGeneratedPass2CodeFileBackup"},{"SubCategory":null,"ErrorCode":null,"HelpKeyword":null,"File":null,"LineNumber":0,"ColumnNumber":0,"EndLineNumber":0,"EndColumnNumber":0,"Message":"Xaml Compiler Marker: 14:58:59: 439 perfXC_RestoredTypeInfoBackup"}]}